saleor_sdk/__init__.py
saleor_sdk/__main__.py
saleor_sdk/console/app.py
saleor_sdk/console/tools.py
saleor_sdk/crypto/exceptions.py
saleor_sdk/crypto/utils.py
saleor_sdk/marina/__init__.py
saleor_sdk/marina/auth.py
saleor_sdk/marina/client.py
saleor_sdk/marina/config.py
saleor_sdk/marina/exceptions.py
saleor_sdk/marina/install.py
saleor_sdk/marina/jwks.py
saleor_sdk/marina/utils.py
saleor_sdk/schemas/__init__.py
saleor_sdk/schemas/enums.py
saleor_sdk/schemas/manifest.py
saleor_sdk_python-0.2.1.dist-info/METADATA
saleor_sdk_python-0.2.1.dist-info/WHEEL
saleor_sdk_python-0.2.1.dist-info/entry_points.txt
saleor_sdk_python-0.2.1.dist-info/licenses/LICENSE
saleor_sdk_python-0.2.1.dist-info/RECORD
