Metadata-Version: 2.1
Name: saleor-sdk-python
Version: 0.2.1
Summary: A set of helpers and tools for a Saleor related Python project.
Project-URL: Repository, https://github.com/mirumee/saleor-sdk-python
Project-URL: Bug Tracker, https://github.com/mirumee/saleor-sdk-python/issues
Project-URL: Community, https://github.com/mirumee/saleor-sdk-python/discussions
Author-email: Mirumee Software <hello@mirumee.com>
License: BSD 3-Clause License
License-File: LICENSE
Classifier: Development Status :: 4 - Beta
Classifier: Intended Audience :: Developers
Classifier: License :: OSI Approved :: BSD License
Classifier: Operating System :: OS Independent
Classifier: Programming Language :: Python
Classifier: Programming Language :: Python :: 3.10
Classifier: Programming Language :: Python :: 3.11
Classifier: Programming Language :: Python :: 3.12
Classifier: Topic :: Software Development :: Libraries :: Python Modules
Requires-Python: >=3.10
Requires-Dist: click~=8.0
Requires-Dist: cryptography>=39
Requires-Dist: pydantic~=2.0
Requires-Dist: pyjwt~=2.8
Requires-Dist: toml~=0.10
